[
 {
  "id": 1,
  "firstName": "Mark",
  "lastName": "Otto",
  "password": "123123",
  "cPassword": "123123",
  "phone": "1212121212",
  "birthdate": "1212-12-12",
  "city": "new city",
  "email": "otoo@gmail.com"
 },
 {
  "id": 2,
  "firstName": "Mark",
  "lastName": "Otto",
  "password": "123123",
  "cPassword": "123123",
  "phone": "123123123123",
  "birthdate": "1224-12-12",
  "city": "New Ortuzar",
  "email": "chinchopa@gmail.com",
  "image": "thumbnail_IMG_5477.jpg"
 },
 {
  "id": 3,
  "firstName": "Mark",
  "lastName": "Otto",
  "password": "dadadad",
  "cPassword": "dadadada",
  "phone": "123123",
  "birthdate": "2023-01-13",
  "city": "addada",
  "email": "d3@gmail.com",
  "image": "thumbnail_IMG_5477.jpg"
 },
 {
  "id": 4,
  "firstName": "Mark",
  "lastName": "Otto",
  "password": "1e1231",
  "cPassword": "e13e13e",
  "phone": "123312",
  "birthdate": "1232-03-12",
  "city": "12312dqw",
  "email": "dede@gasd.com",
  "image": "p1m1br7rl8r51.jpg"
 },
 {
  "id": 5,
  "firstName": "Mark",
  "lastName": "Otto",
  "password": "|123123",
  "cPassword": "1232|321",
  "phone": "1231231",
  "birthdate": "12312-12-12",
  "city": "awdawd",
  "email": "qdwqd@gasd.com",
  "image": "thumbnail_IMG_5477.jpg"
 },
 {
  "id": 6,
  "firstName": "Mark",
  "lastName": "Otto",
  "password": "qwdqw",
  "cPassword": "qwdqwdqw",
  "phone": "213213",
  "birthdate": "1212-12-12",
  "city": "dqdwdwq",
  "email": "wqdqwd@asd.com",
  "image": "thumbnail_IMG_5477.jpg"
 },
 {
  "id": 7,
  "firstName": "Julian Pablo",
  "lastName": "Barzana",
  "password": "qwdqwdqwdqwd",
  "cPassword": "qddwqqwd",
  "phone": "01136917222",
  "birthdate": "2013-02-07",
  "city": "Villa Ortuzar",
  "email": "julianmod@hotmail.com"
 },
 {
  "id": 8,
  "firstName": "Julian Pablo",
  "lastName": "Barzana",
  "password": "e12e12edqw",
  "cPassword": "qwdwdq",
  "phone": "01136917222",
  "birthdate": "2005-07-08",
  "city": "Villa Ortuzar",
  "email": "julianmod@hotmail.com",
  "image": "thumbnail_IMG_5477.jpg"
 },
 {
  "id": 10,
  "firstName": "Julian",
  "lastName": "Barzana",
  "password": "$2a$10$Dj3ARM87iy83UmTqseEqCeCtlBC4j2IrWDAY2dKgszzWmfk/BS6QK",
  "cPassword": "asdasdasdasd",
  "phone": "01136917222",
  "birthdate": "2023-01-11",
  "city": "Buenos Aires",
  "email": "julianbarz97@gmail.com",
  "image": "Capture.PNG"
 },
 {
  "id": 11,
  "firstName": "Julian Pablo",
  "lastName": "Barzana",
  "password": "$2a$10$GgB1V3WJWuuDr2KDDyXZu.DP1YHnKEyv6s670BkwqAG8V8y7BE1lO",
  "cPassword": "123",
  "phone": "01136917222",
  "birthdate": "2023-01-22",
  "city": "Villa Ortuzar",
  "email": "julianmod@hotmail.com",
  "image": "Capture.PNG"
 },
 {
  "id": 12,
  "firstName": "Julian Pablo",
  "lastName": "Barzana",
  "password": "$2a$10$HQIRlVDaw/cg9MWbOLGlKe8QDK2S7DSxTaeeXcQo5AtQuEDmtgsD2",
  "cPassword": "123",
  "phone": "01136917222",
  "birthdate": "2023-01-15",
  "city": "Villa Ortuzar",
  "email": "julianmod@hotmail.com",
  "image": "Capture.PNG"
 },
 {
  "id": 13,
  "firstName": "Julian Pablo",
  "lastName": "",
  "password": "$2a$10$NC7GZdQEUvpipS4.PB5Ja.5.yoHUTbJeNssliwiPXdVv1tw6uPuay",
  "cPassword": "123123",
  "phone": "01136917222",
  "birthdate": "2023-01-14",
  "city": "Villa Ortuzar",
  "email": "julianmod@hotmail.com",
  "image": "Capture.PNG"
 },
 {
  "id": 14,
  "firstName": "Julian Pablo",
  "lastName": "Barzana",
  "password": "$2a$10$dlcT2MyqO6cdy7ZRttIKfuSWbY5AYioDEcjU6Pe3odIHosNSD07yy",
  "cPassword": "123",
  "phone": "01136917222",
  "birthdate": "2022-12-30",
  "city": "Villa Ortuzar",
  "email": "julianmod@hotmail.com",
  "image": "Capture.PNG"
 },
 {
  "id": 15,
  "firstName": "Julian Pablo",
  "lastName": "Barzana",
  "password": "$2a$10$/R3g3istYPguh/GKekF9/OuK7HAbB6/ygHydUIoq6iKYoq0PST3oC",
  "cPassword": "123123",
  "phone": "01136917222",
  "birthdate": "2023-01-20",
  "city": "Villa Ortuzar",
  "email": "julianmod@hotmail.com",
  "image": "Capture.PNG"
 },
 {
  "id": 16,
  "firstName": "Julian Pablo",
  "lastName": "Barzana",
  "password": "$2a$10$e9gpXj/XFKWLwe0C1fgQI.PqMdGExzhjGj/cpY8jaYJ.rY8kR7mui",
  "cPassword": "123123",
  "phone": "01136917222",
  "birthdate": "2023-01-22",
  "city": "Villa Ortuzar",
  "email": "julianmod@hotmail.com",
  "image": "Capture.PNG"
 },
 {
  "id": 17,
  "firstName": "Julian Pablo",
  "lastName": "Barzana",
  "password": "$2a$10$ej3xdtMmowPrFPprKzRAt.ivEZ26dJA.cLkcKXbtswfd9IhvmRRqG",
  "cPassword": "123123",
  "phone": "01136917222",
  "birthdate": "2023-01-22",
  "city": "Villa Ortuzar",
  "email": "julianmod@hotmail.com"
 },
 {
  "id": 18,
  "firstName": "Julian Pablo",
  "lastName": "Barzana",
  "password": "$2a$10$RI.078O9BCvJ55ZqXFSvseDeX9ifYEB.b7Li.eNKOsHSG4/xzZjlW",
  "cPassword": "12123",
  "phone": "1123123",
  "birthdate": "0012-12-12",
  "city": "Villa Ortuzar",
  "email": "123@gmail.com"
 },
 {
  "id": 19,
  "firstName": "Mark",
  "lastName": "Chancho",
  "password": "$2a$10$NDw.NXYwZcEPCe2XPleOTuPQh17orQ/WJaYmaQPPwHnTXwhD/Tjwa",
  "cPassword": "asdasdasd",
  "phone": "01136917222",
  "birthdate": "2023-01-11",
  "city": "Villa Ortuzar",
  "email": "chanchova@gmail.com"
 },
 {
  "id": 20,
  "firstName": "Julian",
  "lastName": "Barzana",
  "password": "$2a$10$zLO/DljvKbX0dtCt1WzGIuBHqx2DxAbKfomy.86kUCdRTeC3/oDQq",
  "cPassword": "123123123",
  "phone": "1136917221",
  "birthdate": "2023-01-28",
  "city": "Buenos Aires",
  "email": "mark@gmail.com"
 },
 {
  "id": 21,
  "firstName": "siusius",
  "lastName": "siusius",
  "email": "siu@gmail.com",
  "password": "siusiu",
  "cPassword": "siusius",
  "birthdate": "2023-01-10",
  "city": "Buenos Aires",
  "phone": "01136917222"
 },
 {
  "id": 22,
  "firstName": "admin",
  "lastName": "admin",
  "email": "admin@gmail.com",
  "password": "$2a$10$s2q/Yyr1teOsk71U8L3aMOJLacWL8ARlSfrUyn7ApJ30y1m4U3MxW",
  "cPassword": "admin123",
  "birthdate": "2023-01-19",
  "city": "admin",
  "phone": "1111"
 },
 {
  "id": 23,
  "firstName": "Mark",
  "lastName": "Otto",
  "email": "markman@gmail.com",
  "password": "$2a$10$IwbgrBRY0trHDn4vJqTBzu23LDyl2yDgfrO0Y3E55rg18Eood0NQC",
  "cPassword": "Znpodkwa1",
  "birthdate": "2023-01-13",
  "city": "New Gerd",
  "phone": "01122334455"
 },
 {
  "id": 24,
  "firstName": "Super",
  "lastName": "Mario",
  "email": "mariochan@gmail.com",
  "password": "$2a$10$aaMxzk3QL.ZM1F2Cg1muruywNLyhJLI1pyHZpSmlJuDP364oBoF4y",
  "cPassword": "mario",
  "birthdate": "2022-12-30",
  "city": "Buenos Aires",
  "phone": "2233445566",
  "image": "1674585157095_img.jpg"
 },
 {
  "id": 25,
  "firstName": "Master",
  "lastName": "Plan",
  "email": "Plan@gmail.com",
  "password": "$2a$10$Q9vTJEr6tZxCVVHDK8BzTuaEfgnSALtwrI4O/A1QVR.pNFxcVU.O.",
  "cPassword": "Znpodkwa123",
  "birthdate": "2023-01-11",
  "city": "Buenos Aires",
  "phone": "23232323",
  "image": "1674585607490_img.JPG"
 },
 {
  "id": 26,
  "firstName": "Julian",
  "lastName": "Barzana",
  "email": "julian@gmail.com",
  "password": "$2a$10$1yzw6TgUBMm3.eTmjZ9H..VHCW9yF7YAp6kLuF9ePts1N3TXs8jm6",
  "cPassword": "Znpodkwa123",
  "birthdate": "1995-10-08",
  "city": "Villa Ortuzar",
  "phone": "01136917222",
  "image": "1675529706302_img.jpg"
 },
 {
  "id": 27,
  "firstName": "Julian Pablo",
  "lastName": "Barzana",
  "email": "juliandsdsdd@hotmail.com",
  "password": "$2a$10$WSbsPzvD7.hun61sDTZHXOMXpx9AkmxBeEfkz.CXPAlg9M9gln3dG",
  "cPassword": "sd",
  "birthdate": "2023-03-01",
  "city": "Villa Ortuzar",
  "phone": "01136917222",
  "image": "1675644904943_img.png"
 },
 {
  "id": 28,
  "firstName": "Julian Pablo",
  "lastName": "Barzana",
  "email": "julianmod@hotasdasdmail.com",
  "password": "$2a$10$l2lDY4ttXydRkv7gCBiOUu2IysKe0qS0Fs8culGQ1kOxD2M/pCOcm",
  "cPassword": "sdd",
  "birthdate": "2022-08-11",
  "city": "Villa Ortuzar",
  "phone": "01136917222",
  "image": "1675645023591_img.png"
 },
 {
  "id": 29,
  "firstName": "Julian Pablo",
  "lastName": "Barzana",
  "email": "julid@hotmail.com",
  "password": "$2a$10$kbpKeEeQ.vLg5AWWWXvHxua3A72j6kMCe94KOntYB86jvQ7kgx5Sm",
  "cPassword": "as",
  "birthdate": "2023-02-23",
  "city": "Villa Ortuzar",
  "phone": "01136917222",
  "image": "1675645141224_img.png"
 },
 {
  "id": 30,
  "firstName": "Julian Pablo",
  "lastName": "Barzana",
  "email": "julianm123123od@hotmail.com",
  "password": "$2a$10$l4iwOAmEZ7kgs59AH4TSSOYK0caUgZWmuuXJ.p5q3QkWRS4D./a3S",
  "cPassword": "131",
  "birthdate": "2022-09-16",
  "city": "Villa Ortuzar",
  "phone": "01136917222",
  "image": "1675645188332_img.png"
 },
 {
  "id": 31,
  "firstName": "Julian Pablo",
  "lastName": "Barzana",
  "email": "anmod@hotmail.com",
  "password": "$2a$10$.pnM6M90Df8sxlAz165Rt.MsY3Glq7f5.iFPmVVe8/jt.6qeLuGhi",
  "cPassword": "dd",
  "birthdate": "2019-06-05",
  "city": "Villa Ortuzar",
  "phone": "01136917222",
  "image": "1675645239128_img.png"
 },
 {
  "id": 32,
  "firstName": "Julian Pablo",
  "lastName": "Barzana",
  "email": "jul@hotmail.com",
  "password": "$2a$10$CTR.hKVIjqx3iRNsl5e63.N.LVZhuB..SjsV5hUzD51sGW9dKoXmO",
  "cPassword": "asdasd",
  "birthdate": "2023-02-22",
  "city": "Villa Ortuzar",
  "phone": "01136917222",
  "image": "1675649328855_img.png"
 },
 {
  "id": 33,
  "firstName": "Julian Pablo",
  "lastName": "Barzana",
  "email": "julssianmod@hotmail.com",
  "password": "$2a$10$OgI0mATxVki2W0W03AgliOt.HxFgM9NpW52Crl52mk/u5DKd0X6oq",
  "cPassword": "ssss",
  "birthdate": "2023-03-05",
  "city": "Villa Ortuzar",
  "phone": "01136917222",
  "image": "1675649411896_img.png"
 },
 {
  "id": 34,
  "firstName": "Julian Pablo",
  "lastName": "Barzana",
  "email": "juliaasdasdnmod@hotmail.com",
  "password": "$2a$10$plhI.alBhAWr9KCRbMCBnOw/YVnEsPPIN/bY8et6IL4eMT4cf8C9q",
  "cPassword": "asdasd",
  "birthdate": "2023-02-25",
  "city": "Villa Ortuzar",
  "phone": "01136917222",
  "image": "1675649461091_img.png"
 },
 {
  "id": 35,
  "firstName": "Julian Pablo",
  "lastName": "Barzana",
  "email": "julianmssd@hotmail.com",
  "password": "$2a$10$4P93mLMQECUPA3jSGN4KTuLlMKVm56QJTYP929UC7xQPFVLcspv2m",
  "cPassword": "ss",
  "birthdate": "2023-03-03",
  "city": "Villa Ortuzar",
  "phone": "01136917222",
  "image": "1675649537457_img.png"
 },
 {
  "id": 36,
  "firstName": "Julian Pablo",
  "lastName": "Barzana",
  "email": "asdasdasdasd@hotmail.com",
  "password": "$2a$10$AXKDkygI2/wxN7VOvgBszerC7i0f7WeXHfn38/Ss.xORTP/BPh4By",
  "cPassword": "asd",
  "birthdate": "2023-02-17",
  "city": "Villa Ortuzar",
  "phone": "01136917222",
  "image": "1675717102942_img.png"
 },
 {
  "id": 37,
  "firstName": "Julian Pablo",
  "lastName": "Barzana",
  "email": "julisssanmod@hotmail.com",
  "password": "$2a$10$wXhdU6OIg9Hchr57A6H/veuWy6CLBRANpVIV9eu4E.m0ZMvVpGjYG",
  "cPassword": "sd123",
  "birthdate": "2023-02-24",
  "city": "Villa Ortuzar",
  "phone": "01136917222",
  "image": "1675721461222_img.png"
 },
 {
  "id": 38,
  "firstName": "Julian Pablo",
  "lastName": "Barzana",
  "email": "juliansdsdsdsdsdsmod@hotmail.com",
  "password": "$2a$10$vdMaoFIf2jlcVxM9W/Dg0OT0rNKhxQ53z7XHbuZo5lmny9c6/EnX6",
  "cPassword": "123123",
  "birthdate": "2023-02-17",
  "city": "Villa Ortuzar",
  "phone": "01136917222",
  "image": "1675721532685_img.png"
 },
 {
  "id": 39,
  "firstName": "Julian Pablo",
  "lastName": "Barzana",
  "email": "juliaaanmod@hotmail.com",
  "password": "$2a$10$/nd1GUopB.qA.cLAkz69weXWqTj0R22g9Gz9cwTy5SjJQFvRniJHO",
  "cPassword": "123123",
  "birthdate": "2023-02-02",
  "city": "Villa Ortuzar",
  "phone": "01136917222",
  "image": "1675721582786_img.png"
 },
 {
  "id": 40,
  "firstName": "chanchoasd",
  "lastName": "chanchoasd",
  "email": "chanchito@gmail.com",
  "password": "$2a$10$28Uyvt8mmSRPtHB06pNrU.vkhM535J/TIMa7CG/rhCl6eCV0ptZau",
  "cPassword": "Znpodkwa123",
  "birthdate": "01-01-2000",
  "sex": "Male",
  "city": "Villa Ortuzar",
  "phone": "01136917222",
  "image": "1676308788803_img.jpg"
 }
]